wideq.py
wideqlg-1.0.0.dist-info/LICENSE
wideqlg-1.0.0.dist-info/METADATA
wideqlg-1.0.0.dist-info/WHEEL
wideqlg-1.0.0.dist-info/top_level.txt
wideqlg-1.0.0.dist-info/RECORD
